package_updater/__init__.py
package_updater/package_updater.py
package_updater-0.0.3.dist-info/METADATA
package_updater-0.0.3.dist-info/RECORD
package_updater-0.0.3.dist-info/WHEEL
package_updater-0.0.3.dist-info/top_level.txt
